sphinxcontrib_vcs-0.2.2-py3.7-nspkg.pth
sphinxcontrib/vcs.py
sphinxcontrib/_static/contrib-vcs.css
sphinxcontrib/_static/contrib-vcs.js
sphinxcontrib/repository/__init__.py
sphinxcontrib/repository/_git.py
sphinxcontrib/repository/utils.py
sphinxcontrib_vcs-0.2.2.dist-info/LICENSE
sphinxcontrib_vcs-0.2.2.dist-info/METADATA
sphinxcontrib_vcs-0.2.2.dist-info/WHEEL
sphinxcontrib_vcs-0.2.2.dist-info/namespace_packages.txt
sphinxcontrib_vcs-0.2.2.dist-info/top_level.txt
sphinxcontrib_vcs-0.2.2.dist-info/RECORD
