Metadata-Version: 2.1
Name: sphinxcontrib-vcs
Version: 0.2.2
Summary: Sphinx extension to show commit history in version control system
Home-page: https://github.com/t2y/sphinxcontrib-vcs
Author: Tetsuya Morimoto
Author-email: tetsuya.morimoto@gmail.com
License: BSD
Platform: any
Classifier: License :: OSI Approved :: BSD License
Classifier: Development Status :: 4 - Beta
Classifier: Intended Audience :: Developers
Classifier: Operating System :: OS Independent
Classifier: Programming Language :: Python :: 3
Classifier: Programming Language :: Python :: 3.5
Classifier: Programming Language :: Python :: 3.6
Classifier: Programming Language :: Python :: 3.7
Classifier: Programming Language :: Python :: Implementation :: CPython
Classifier: Topic :: Software Development :: Libraries
Classifier: Environment :: Console
Classifier: Framework :: Sphinx :: Extension
Classifier: Topic :: Documentation
Classifier: Topic :: Documentation :: Sphinx
Classifier: Topic :: Utilities
Requires-Dist: GitPython
Requires-Dist: Sphinx
